integv/__init__.py
integv/_base.py
integv/_common.py
integv/_file.py
integv/exception.py
integv/mime.types
integv/audio/__init__.py
integv/audio/_audio.py
integv/image/__init__.py
integv/image/_image.py
integv/video/__init__.py
integv/video/_video.py
integv-1.3.0.dist-info/LICENSE
integv-1.3.0.dist-info/METADATA
integv-1.3.0.dist-info/WHEEL
integv-1.3.0.dist-info/top_level.txt
integv-1.3.0.dist-info/RECORD
